aws_textract_pipeline/__init__.py
aws_textract_pipeline/_version.py
aws_textract_pipeline/api.py
aws_textract_pipeline/doc_type.py
aws_textract_pipeline/landing.py
aws_textract_pipeline/logger.py
aws_textract_pipeline/paths.py
aws_textract_pipeline/segment.py
aws_textract_pipeline/tracker.py
aws_textract_pipeline/workspace.py
aws_textract_pipeline/docs/__init__.py
aws_textract_pipeline/tests/__init__.py
aws_textract_pipeline/tests/helper.py
aws_textract_pipeline/tests/mock_test.py
aws_textract_pipeline/vendor/__init__.py
aws_textract_pipeline/vendor/better_dataclasses.py
aws_textract_pipeline/vendor/better_enum.py
aws_textract_pipeline/vendor/hashes.py
aws_textract_pipeline/vendor/mock_aws.py
aws_textract_pipeline/vendor/nested_logger.py
aws_textract_pipeline/vendor/pytest_cov_helper.py
aws_textract_pipeline-0.4.1.dist-info/AUTHORS.rst
aws_textract_pipeline-0.4.1.dist-info/LICENSE.txt
aws_textract_pipeline-0.4.1.dist-info/METADATA
aws_textract_pipeline-0.4.1.dist-info/WHEEL
aws_textract_pipeline-0.4.1.dist-info/top_level.txt
aws_textract_pipeline-0.4.1.dist-info/RECORD
