Metadata-Version: 2.1
Name: aws_textract_pipeline
Version: 0.4.1
Summary: Package short description.
Home-page: https://github.com/MacHu-GWU/aws_textract_pipeline-project
Download-URL: https://pypi.python.org/pypi/aws_textract_pipeline/0.4.1#downloads
Author: Sanhe Hu
Author-email: husanhe@gmail.com
Maintainer: Sanhe Hu
Maintainer-email: husanhe@gmail.com
License: MIT
Platform: Windows
Platform: MacOS
Platform: Unix
Classifier: Development Status :: 4 - Beta
Classifier: Intended Audience :: Developers
Classifier: License :: OSI Approved :: MIT License
Classifier: Natural Language :: English
Classifier: Operating System :: Microsoft :: Windows
Classifier: Operating System :: MacOS
Classifier: Operating System :: Unix
Classifier: Programming Language :: Python
Classifier: Programming Language :: Python :: 3.8
Classifier: Programming Language :: Python :: 3.9
Classifier: Programming Language :: Python :: 3.10
Classifier: Programming Language :: Python :: 3.11
Classifier: Programming Language :: Python :: 3.12
Classifier: Programming Language :: Python :: 3 :: Only
Requires-Python: >=3.8
License-File: LICENSE.txt
License-File: AUTHORS.rst
Requires-Dist: aws-textract <1.0.0,>=0.2.1
Requires-Dist: pynamodb <6.0.0,>=5.5.1
Requires-Dist: pynamodb-mate ==5.3.4.9
Requires-Dist: boto-session-manager <2.0.0,>=1.7.2
Requires-Dist: s3pathlib <3.0.0,>=2.1.2
Requires-Dist: PyMuPDF <2.0.0,>=1.23.26
Requires-Dist: python-docx <2.0.0,>=1.0.1
Requires-Dist: openpyxl <4.0.0,>=3.0.10
Requires-Dist: python-pptx <1.0.0,>=0.6.23
Requires-Dist: pillow <10.0.0,>=9.5.0
Provides-Extra: docs
Requires-Dist: Sphinx ==5.3.0 ; extra == 'docs'
Requires-Dist: sphinx-jinja ==2.0.2 ; extra == 'docs'
Requires-Dist: sphinx-copybutton ==0.5.1 ; extra == 'docs'
Requires-Dist: sphinx-design ==0.5.0 ; extra == 'docs'
Requires-Dist: furo ==2023.03.27 ; extra == 'docs'
Requires-Dist: nbsphinx ==0.8.12 ; extra == 'docs'
Requires-Dist: rstobj ==1.2.1 ; extra == 'docs'
Requires-Dist: pygments ==2.15.1 ; extra == 'docs'
Requires-Dist: ipython ==8.10.0 ; extra == 'docs'
Requires-Dist: docfly ==2.0.3 ; extra == 'docs'
Provides-Extra: tests
Requires-Dist: pytest ; extra == 'tests'
Requires-Dist: pytest-cov ; extra == 'tests'
Requires-Dist: moto <5.0.0,>=4.2.14 ; extra == 'tests'
